LICENSE
MANIFEST.in
README.md
requirements.txt
setup.py
version.txt
gh_whid.egg-info/PKG-INFO
gh_whid.egg-info/SOURCES.txt
gh_whid.egg-info/dependency_links.txt
gh_whid.egg-info/entry_points.txt
gh_whid.egg-info/requires.txt
gh_whid.egg-info/top_level.txt
whid/__init__.py
whid/cli/__init__.py
whid/cli/cli.py
whid/core/__init__.py
whid/core/chatgpt.py
whid/core/crendential.py
whid/core/github.py