Metadata-Version: 2.1
Name: gh-whid
Version: 0.0.4
Summary: What have I done - Summarizer for Your GitHub Pull Request Activities
Home-page: https://github.com/hpcaitech/gh-whid
License: Apache Software License 2.0
Project-URL: Github, https://github.com/hpcaitech/gh-whid
Platform: UNKNOWN
Classifier: Programming Language :: Python :: 3
Classifier: License :: OSI Approved :: Apache Software License
Classifier: Environment :: GPU :: NVIDIA CUDA
Classifier: Topic :: Scientific/Engineering :: Artificial Intelligence
Classifier: Topic :: System :: Distributed Computing
Requires-Python: >=3.6
